unidown_mr_de/__init__.py
unidown_mr_de/exceptions.py
unidown_mr_de/link_item.py
unidown_mr_de/meta.py
unidown_mr_de/plugin.py
unidown_mr_de/tools.py
unidown_mr_de-1.1.0.dist-info/LICENSE.md
unidown_mr_de-1.1.0.dist-info/METADATA
unidown_mr_de-1.1.0.dist-info/WHEEL
unidown_mr_de-1.1.0.dist-info/entry_points.txt
unidown_mr_de-1.1.0.dist-info/top_level.txt
unidown_mr_de-1.1.0.dist-info/zip-safe
unidown_mr_de-1.1.0.dist-info/RECORD
