Metadata-Version: 2.1
Name: unidown-mr-de
Version: 1.1.0
Summary: MR german books plugin for unidown.
Home-page: https://github.com/IceflowRE/unidown-mr_de
Author: Iceflower S
Author-email: iceflower@gmx.de
License: GPLv3
Keywords: plugin unidown
Platform: UNKNOWN
Classifier: Programming Language :: Python :: 3.8
Classifier: License :: OSI Approved :: GNU General Public License v3 (GPLv3)
Classifier: Development Status :: 5 - Production/Stable
Classifier: Operating System :: OS Independent
Classifier: Intended Audience :: End Users/Desktop
Classifier: Natural Language :: English
Classifier: Natural Language :: German
Classifier: Environment :: Console
Requires-Python: >=3.8
License-File: LICENSE.md
Requires-Dist: unidown (==2.1.0)
Requires-Dist: urllib3 (>=1.26.7)
Requires-Dist: tqdm (>=4.62.3)
Requires-Dist: beautifulsoup4 (>=4.10.0)
Requires-Dist: lxml (>=4.7.1)
Requires-Dist: certifi
Provides-Extra: dev
Requires-Dist: flake8 (==4.0.1) ; extra == 'dev'
Requires-Dist: pylint (==2.12.2) ; extra == 'dev'
Requires-Dist: pyroma (==3.2) ; extra == 'dev'
Requires-Dist: twine (==3.7.1) ; extra == 'dev'
Requires-Dist: setuptools (==59.6.0) ; extra == 'dev'
Requires-Dist: wheel (==0.37.0) ; extra == 'dev'
